ligandmpnn/__init__.py
ligandmpnn/run.py
ligandmpnn/data/__init__.py
ligandmpnn/data/model_params/__init__.py
ligandmpnn/data/model_params/global_label_membrane_mpnn_v_48_020.pt
ligandmpnn/data/model_params/ligandmpnn_sc_v_32_002_16.pt
ligandmpnn/data/model_params/ligandmpnn_v_32_005_25.pt
ligandmpnn/data/model_params/ligandmpnn_v_32_010_25.pt
ligandmpnn/data/model_params/ligandmpnn_v_32_020_25.pt
ligandmpnn/data/model_params/ligandmpnn_v_32_030_25.pt
ligandmpnn/data/model_params/per_residue_label_membrane_mpnn_v_48_020.pt
ligandmpnn/data/model_params/proteinmpnn_v_48_002.pt
ligandmpnn/data/model_params/proteinmpnn_v_48_010.pt
ligandmpnn/data/model_params/proteinmpnn_v_48_020.pt
ligandmpnn/data/model_params/proteinmpnn_v_48_030.pt
ligandmpnn/data/model_params/solublempnn_v_48_002.pt
ligandmpnn/data/model_params/solublempnn_v_48_010.pt
ligandmpnn/data/model_params/solublempnn_v_48_020.pt
ligandmpnn/data/model_params/solublempnn_v_48_030.pt
ligandmpnn/utils/__init__.py
ligandmpnn/utils/data_utils.py
ligandmpnn/utils/model_utils.py
ligandmpnn/utils/sc_utils.py
ligandmpnn/utils/score.py
ligandmpnn/utils/openfold/__init__.py
ligandmpnn/utils/openfold/config.py
ligandmpnn/utils/openfold/data/__init__.py
ligandmpnn/utils/openfold/data/data_modules.py
ligandmpnn/utils/openfold/data/data_pipeline.py
ligandmpnn/utils/openfold/data/data_transforms.py
ligandmpnn/utils/openfold/data/errors.py
ligandmpnn/utils/openfold/data/feature_pipeline.py
ligandmpnn/utils/openfold/data/input_pipeline.py
ligandmpnn/utils/openfold/data/mmcif_parsing.py
ligandmpnn/utils/openfold/data/parsers.py
ligandmpnn/utils/openfold/data/templates.py
ligandmpnn/utils/openfold/data/tools/__init__.py
ligandmpnn/utils/openfold/data/tools/hhblits.py
ligandmpnn/utils/openfold/data/tools/hhsearch.py
ligandmpnn/utils/openfold/data/tools/jackhmmer.py
ligandmpnn/utils/openfold/data/tools/kalign.py
ligandmpnn/utils/openfold/data/tools/utils.py
ligandmpnn/utils/openfold/np/__init__.py
ligandmpnn-0.1.2.dist-info/LICENSE
ligandmpnn-0.1.2.dist-info/METADATA
ligandmpnn-0.1.2.dist-info/WHEEL
ligandmpnn-0.1.2.dist-info/entry_points.txt
ligandmpnn-0.1.2.dist-info/top_level.txt
ligandmpnn-0.1.2.dist-info/RECORD
