Metadata-Version: 2.2
Name: ligandmpnn
Version: 0.1.2
Summary: a pip installable version of LigandMPNN with pre-trained models included
Home-page: https://github.com/dauparas/LigandMPNN
Author: originally and primarily authored by Justas Dauparas. installable version by markus.
Author-email: justas@uw.edu
License: MIT
Classifier: License :: OSI Approved :: MIT License
Classifier: Programming Language :: Python :: 3.11
Classifier: Operating System :: POSIX :: Linux
Classifier: Operating System :: MacOS :: MacOS X
Requires-Python: >=3.11, <3.12
License-File: LICENSE
Requires-Dist: torch==2.2.1
Requires-Dist: biopython==1.79
Requires-Dist: filelock==3.13.1
Requires-Dist: fsspec==2024.3.1
Requires-Dist: Jinja2==3.1.3
Requires-Dist: MarkupSafe==2.1.5
Requires-Dist: mpmath==1.3.0
Requires-Dist: networkx==3.2.1
Requires-Dist: numpy==1.23.5
Requires-Dist: ProDy==2.4.1
Requires-Dist: pyparsing==3.1.1
Requires-Dist: scipy==1.12.0
Requires-Dist: sympy==1.12
Requires-Dist: typing_extensions==4.10.0
Requires-Dist: ml-collections==0.1.1
Requires-Dist: dm-tree==0.1.8
Requires-Dist: setuptools
Provides-Extra: dev
Requires-Dist: pytest>=7.0; extra == "dev"
Requires-Dist: twine>=4.0.2; extra == "dev"
Requires-Dist: pytest-cov>=4.0; extra == "dev"
Requires-Dist: wheel; extra == "dev"
Dynamic: author
Dynamic: author-email
Dynamic: classifier
Dynamic: description
Dynamic: description-content-type
Dynamic: home-page
Dynamic: license
Dynamic: provides-extra
Dynamic: requires-dist
Dynamic: requires-python
Dynamic: summary
